sqlalchemy_query_watch/__init__.py
sqlalchemy_query_watch/check_consecutive_query.py
sqlalchemy_query_watch/query_time_log.py
sqlalchemy_query_watch/statement_count_log.py
sqlalchemy_query_watch-0.0.1.dist-info/LICENSE
sqlalchemy_query_watch-0.0.1.dist-info/METADATA
sqlalchemy_query_watch-0.0.1.dist-info/WHEEL
sqlalchemy_query_watch-0.0.1.dist-info/top_level.txt
sqlalchemy_query_watch-0.0.1.dist-info/RECORD
