Metadata-Version: 2.1
Name: sqlalchemy-query-watch
Version: 0.0.1
Summary: Subscribe query log to SqlAlchemy event
Author: Mick Mak
Author-email: mk.triniti@gmail.com
Keywords: python,sqlalchemy,log
License-File: LICENSE
Requires-Dist: sqlalchemy (>=2.0.18)
